zvic/__init__.py
zvic/annotation_constraints.py
zvic/compatibility.py
zvic/compatibility_constraints.py
zvic/compatibility_params.py
zvic/compatibility_types.py
zvic/crosshair_subprocess.py
zvic/exception.py
zvic/main.py
zvic/utils.py
zvic-2025.34.2.dist-info/licenses/LICENSE
zvic-2025.34.2.dist-info/METADATA
zvic-2025.34.2.dist-info/WHEEL
zvic-2025.34.2.dist-info/top_level.txt
zvic-2025.34.2.dist-info/RECORD
