Metadata-Version: 2.4
Name: zvic
Version: 2025.34.2
Summary: Zero-Version Interface Contracts (ZVIC) - signature-based compatibility for Python modules.
Author: Anselm Kiefner
License-Expression: MIT
Classifier: Programming Language :: Python :: 3
Classifier: Operating System :: OS Independent
Requires-Python: >=3.12
License-File: LICENSE
Provides-Extra: crosshair
Requires-Dist: crosshair-tool; extra == "crosshair"
Dynamic: license-file
